wavespectra2dsplitfit/S2DFit.py
wavespectra2dsplitfit/__init__.py
wavespectra2dsplitfit-0.5.7.dist-info/AUTHORS.rst
wavespectra2dsplitfit-0.5.7.dist-info/LICENSE
wavespectra2dsplitfit-0.5.7.dist-info/METADATA
wavespectra2dsplitfit-0.5.7.dist-info/WHEEL
wavespectra2dsplitfit-0.5.7.dist-info/top_level.txt
wavespectra2dsplitfit-0.5.7.dist-info/RECORD
