Metadata-Version: 2.1
Name: wavespectra2dsplitfit
Version: 0.5.7
Summary: Ocean wave 2D spectrum partitioning and fitting JONSWAP spectrum
Author: Jason McConochie
Author-email: Jason McConochie <j.mcconochie@shell.com>
Project-URL: Homepage, https://github.com/jmcconochie/wavespectra2dsplitfit
Requires-Python: >=3.6
License-File: LICENSE
License-File: AUTHORS.rst
Requires-Dist: scipy
Requires-Dist: pandas
Requires-Dist: matplotlib
Requires-Dist: scikit-image
Requires-Dist: scikit-learn
